whatsmyversion
