Metadata-Version: 1.1
Name: whatsmyversion
Version: 0.0.5.post2
Summary: Making versioning easy
Home-page: http://github.com/ericdill/whatsmyversion
Author: Eric Dill
Author-email: thedizzle@gmail.com
License: GPLv3
Platform: UNKNOWN
Classifier: License :: OSI Approved :: GNU General Public License v3 (GPLv3)
Classifier: Topic :: Software Development :: Version Control
